autopxd/__init__.py
autopxd/declarations.py
autopxd/keywords.py
autopxd/nodes.py
autopxd/writer.py
autopxd/include/_ansi.h
autopxd/include/_fake_defines.h
autopxd/include/_fake_typedefs.h
autopxd/include/_syslist.h
autopxd/include/aio.h
autopxd/include/alloca.h
autopxd/include/ar.h
autopxd/include/argz.h
autopxd/include/assert.h
autopxd/include/complex.h
autopxd/include/cpio.h
autopxd/include/ctype.h
autopxd/include/dirent.h
autopxd/include/dlfcn.h
autopxd/include/emmintrin.h
autopxd/include/endian.h
autopxd/include/envz.h
autopxd/include/errno.h
autopxd/include/fastmath.h
autopxd/include/fcntl.h
autopxd/include/features.h
autopxd/include/fenv.h
autopxd/include/float.h
autopxd/include/fmtmsg.h
autopxd/include/fnmatch.h
autopxd/include/ftw.h
autopxd/include/getopt.h
autopxd/include/glob.h
autopxd/include/grp.h
autopxd/include/iconv.h
autopxd/include/ieeefp.h
autopxd/include/immintrin.h
autopxd/include/inttypes.h
autopxd/include/iso646.h
autopxd/include/langinfo.h
autopxd/include/libgen.h
autopxd/include/libintl.h
autopxd/include/limits.h
autopxd/include/locale.h
autopxd/include/malloc.h
autopxd/include/math.h
autopxd/include/monetary.h
autopxd/include/mqueue.h
autopxd/include/ndbm.h
autopxd/include/netdb.h
autopxd/include/newlib.h
autopxd/include/nl_types.h
autopxd/include/paths.h
autopxd/include/poll.h
autopxd/include/process.h
autopxd/include/pthread.h
autopxd/include/pwd.h
autopxd/include/reent.h
autopxd/include/regdef.h
autopxd/include/regex.h
autopxd/include/sched.h
autopxd/include/search.h
autopxd/include/semaphore.h
autopxd/include/setjmp.h
autopxd/include/signal.h
autopxd/include/smmintrin.h
autopxd/include/spawn.h
autopxd/include/stdalign.h
autopxd/include/stdarg.h
autopxd/include/stdatomic.h
autopxd/include/stdbool.h
autopxd/include/stddef.h
autopxd/include/stdint.h
autopxd/include/stdio.h
autopxd/include/stdlib.h
autopxd/include/stdnoreturn.h
autopxd/include/string.h
autopxd/include/strings.h
autopxd/include/stropts.h
autopxd/include/syslog.h
autopxd2-2.4.0.dist-info/LICENSE
autopxd2-2.4.0.dist-info/METADATA
autopxd2-2.4.0.dist-info/WHEEL
autopxd2-2.4.0.dist-info/entry_points.txt
autopxd2-2.4.0.dist-info/top_level.txt
autopxd2-2.4.0.dist-info/RECORD
