Metadata-Version: 2.1
Name: autopxd2
Version: 2.4.0
Summary: Automatically generate Cython pxd files from C headers
Home-page: https://github.com/elijahr/python-autopxd2
Author: Elijah Shaw-Rutschman
Author-email: elijahr+autopxd2@gmail.com
License: MIT
Keywords: autopxd,autopxd2,cython,code-generators
Classifier: Topic :: Software Development :: Compilers
Classifier: Topic :: Software Development :: Code Generators
Classifier: Programming Language :: Python :: 3 :: Only
Classifier: Programming Language :: Cython
Classifier: Programming Language :: C
Classifier: Programming Language :: C++
Requires-Python: <4,>=3.6
License-File: LICENSE
Requires-Dist: Click
Requires-Dist: pycparser
Provides-Extra: dev
Requires-Dist: pytest ; extra == 'dev'
Requires-Dist: cython ; extra == 'dev'
